topsis_vansh/__init__.py
topsis_vansh/topsis.py
topsis_vansh_102303641-0.0.1.dist-info/licenses/LICENSE
topsis_vansh_102303641-0.0.1.dist-info/METADATA
topsis_vansh_102303641-0.0.1.dist-info/WHEEL
topsis_vansh_102303641-0.0.1.dist-info/entry_points.txt
topsis_vansh_102303641-0.0.1.dist-info/top_level.txt
topsis_vansh_102303641-0.0.1.dist-info/RECORD
